mlora_cli/__init__.py
mlora_cli/adapter.py
mlora_cli/dataset.py
mlora_cli/dispatcher.py
mlora_cli/file.py
mlora_cli/setting.py
mlora_cli/shell.py
mlora_cli/task.py
mlora_cli-0.2.4.dist-info/LICENSE
mlora_cli-0.2.4.dist-info/METADATA
mlora_cli-0.2.4.dist-info/WHEEL
mlora_cli-0.2.4.dist-info/entry_points.txt
mlora_cli-0.2.4.dist-info/top_level.txt
mlora_cli-0.2.4.dist-info/RECORD
