Metadata-Version: 2.1
Name: mlora_cli
Version: 0.2.4
Summary: The cli tools for mLoRA system.
Project-URL: Homepage, https://github.com/TUDB-Labs/mLoRA
Project-URL: Bug Tracker, https://github.com/TUDB-Labs/mLoRA/issues
Classifier: Programming Language :: Python :: 3
Classifier: License :: OSI Approved :: Apache Software License
Classifier: Operating System :: OS Independent
Requires-Python: >=3.8
License-File: LICENSE
Requires-Dist: requests
Requires-Dist: rich
Requires-Dist: InquirerPy
